core/__init__.py
core/animated_sprite.py
core/asset_manager.py
core/entity.py
core/game.py
core/game_context.py
core/input_manager.py
core/scene.py
core/scene_manager.py
core/settings.py
core/utils.py
core/dataclasses/__init__.py
core/dataclasses/size.py
core/dataclasses/sprite_sheet.py
pygame_core-0.1.32.dist-info/METADATA
pygame_core-0.1.32.dist-info/WHEEL
pygame_core-0.1.32.dist-info/top_level.txt
pygame_core-0.1.32.dist-info/RECORD
