Metadata-Version: 2.1
Name: pygame-core
Version: 0.1.32
Summary: A modular core library for Pygame-based 2D games.
Home-page: https://github.com/Nicklas185105/Pygame-Core
Author: Nicklas Beyer Lydersen
Author-email: nicklasbeyerlydersen@gmail.com
License: MIT
Project-URL: Wiki, https://github.com/Nicklas185105/Pygame-Core/wiki
Project-URL: Source, https://github.com/Nicklas185105/Pygame-Core
Keywords: pygame game development engine
Classifier: Development Status :: 4 - Beta
Classifier: Intended Audience :: Developers
Classifier: Topic :: Games/Entertainment
Classifier: License :: OSI Approved :: MIT License
Classifier: Programming Language :: Python :: 3.10
Requires-Dist: pygame>=2.5.2
Provides-Extra: test
Requires-Dist: pylint; extra == "test"
Requires-Dist: pytest; extra == "test"
Requires-Dist: pytest-pylint; extra == "test"
